README
setup.py
bambu_blog/__init__.py
bambu_blog/admin.py
bambu_blog/apps.py
bambu_blog/context_processors.py
bambu_blog/cron.py
bambu_blog/feeds.py
bambu_blog/forms.py
bambu_blog/helpers.py
bambu_blog/menus.py
bambu_blog/models.py
bambu_blog/querysets.py
bambu_blog/search_indexes.py
bambu_blog/sitemaps.py
bambu_blog/test_models.py
bambu_blog/urls.py
bambu_blog/views.py
bambu_blog/xmlrpc.py
bambu_blog.egg-info/PKG-INFO
bambu_blog.egg-info/SOURCES.txt
bambu_blog.egg-info/dependency_links.txt
bambu_blog.egg-info/requires.txt
bambu_blog.egg-info/top_level.txt
bambu_blog/management/__init__.py
bambu_blog/management/commands/__init__.py
bambu_blog/management/commands/wpimport.py
bambu_blog/migrations/0001_initial.py
bambu_blog/migrations/__init__.py
bambu_blog/static/blog/admin.js
bambu_blog/templates/blog/base.html
bambu_blog/templates/blog/boilerplate-header.inc.html
bambu_blog/templates/blog/boilerplate.html
bambu_blog/templates/blog/post.html
bambu_blog/templates/blog/post.inc.html
bambu_blog/templates/blog/posts-author.html
bambu_blog/templates/blog/posts-category.html
bambu_blog/templates/blog/posts-day.html
bambu_blog/templates/blog/posts-month.html
bambu_blog/templates/blog/posts-tag.html
bambu_blog/templates/blog/posts-year.html
bambu_blog/templates/blog/posts.html
bambu_blog/templates/blog/sidebar.inc.html
bambu_blog/templates/blog/tag-cloud.inc.html
bambu_blog/templates/search/indexes/bambu_blog/post_text.txt
bambu_blog/templatetags/__init__.py
bambu_blog/templatetags/blog.py