Metadata-Version: 1.1
Name: bambu-blog
Version: 3.3.1
Summary: A simple set of models for a basic blog, with some tools for custom-designed blog post writing
Home-page: https://github.com/iamsteadman/bambu-blog
Author: Steadman
Author-email: mark@steadman.io
License: UNKNOWN
Platform: UNKNOWN
Classifier: Development Status :: 4 - Beta
Classifier: Environment :: Web Environment
Classifier: Framework :: Django
